openwillis/gps/__init__.py
openwillis/gps/geolocation_processing.py
openwillis/gps/config/gps.json
openwillis/gps/util/__init__.py
openwillis/gps/util/gps_util.py
openwillis_gps-1.1.0.dist-info/METADATA
openwillis_gps-1.1.0.dist-info/WHEEL
openwillis_gps-1.1.0.dist-info/top_level.txt
openwillis_gps-1.1.0.dist-info/RECORD
