Metadata-Version: 2.4
Name: openwillis-gps
Version: 1.1.0
Summary: digital health measurement
Home-page: https://github.com/bklynhlth/openwillis
Author: bklynhlth
Author-email: admin@bklynhlth.com
License: Apache
Requires-Python: >=3.9, <3.13
Requires-Dist: pandas==2.2.3
Dynamic: author
Dynamic: author-email
Dynamic: description-content-type
Dynamic: home-page
Dynamic: license
Dynamic: requires-dist
Dynamic: requires-python
Dynamic: summary
